odoo/addons/ssi_partner_identification_accountant_certification/README.rst
odoo/addons/ssi_partner_identification_accountant_certification/__init__.py
odoo/addons/ssi_partner_identification_accountant_certification/__manifest__.py
odoo/addons/ssi_partner_identification_accountant_certification/data/res_partner_id_category_data.xml
odoo/addons/ssi_partner_identification_accountant_certification/models/__init__.py
odoo/addons/ssi_partner_identification_accountant_certification/models/res_partner.py
odoo/addons/ssi_partner_identification_accountant_certification/static/description/icon.png
odoo14_addon_ssi_partner_identification_accountant_certification-14.0.1.0.0.dist-info/METADATA
odoo14_addon_ssi_partner_identification_accountant_certification-14.0.1.0.0.dist-info/WHEEL
odoo14_addon_ssi_partner_identification_accountant_certification-14.0.1.0.0.dist-info/top_level.txt
odoo14_addon_ssi_partner_identification_accountant_certification-14.0.1.0.0.dist-info/RECORD
